Metadata-Version: 2.1
Name: revops
Version: 0.0.6
Summary: RevOps Python Client
Home-page: https://github.com/revops-io/revops-python
Author: Adam Ballai
Author-email: adam@revops.io
License: UNKNOWN
Download-URL: https://github.com/revops-io/revops-python/archive/v0.0.6.tar.gz
Platform: UNKNOWN
Classifier: Programming Language :: Python :: 3
Classifier: License :: OSI Approved :: MIT License
Classifier: Operating System :: OS Independent
